Metadata-Version: 2.1
Name: benchmarks-runner
Version: 0.1.3
Summary: Translator Benchmarks Runner
Home-page: https://github.com/TranslatorSRI/Benchmarks
Author: Max Wang
Author-email: max@covar.com
License-File: LICENSE
Requires-Dist: httpx
Requires-Dist: matplotlib
Requires-Dist: numpy
Requires-Dist: reasoner-pydantic
Requires-Dist: requests
Requires-Dist: tqdm
